radarchart/__init__.py
radarchart/main.py
radarchart/ui.py
radarchart_py-0.1.7.dist-info/licenses/LICENSE
radarchart_py-0.1.7.dist-info/METADATA
radarchart_py-0.1.7.dist-info/WHEEL
radarchart_py-0.1.7.dist-info/entry_points.txt
radarchart_py-0.1.7.dist-info/top_level.txt
radarchart_py-0.1.7.dist-info/RECORD
